TPUCameraManager/TPUCameraManager.py
TPUCameraManager/__init__.py
TPUCameraManager/gst.py
TPUCameraManager/gstreamer.py
TPUCameraManager-0.1.1.dist-info/LICENSE
TPUCameraManager-0.1.1.dist-info/METADATA
TPUCameraManager-0.1.1.dist-info/WHEEL
TPUCameraManager-0.1.1.dist-info/top_level.txt
TPUCameraManager-0.1.1.dist-info/RECORD
