Metadata-Version: 2.1
Name: TPUCameraManager
Version: 0.1.1
Summary: A package for camera streams on the google coral
Home-page: https://github.com/pypa/sampleproject
Author: Devin Willis
Author-email: gatordevin@gmail.com
License: UNKNOWN
Platform: UNKNOWN
Classifier: Programming Language :: Python :: 3
Classifier: License :: OSI Approved :: MIT License
Classifier: Operating System :: OS Independent
Requires-Python: >=3.6
